django_mptt_comments/__init__.py
django_mptt_comments/admin.py
django_mptt_comments/apps.py
django_mptt_comments/forms.py
django_mptt_comments/models.py
django_mptt_comments/urls.py
django_mptt_comments/utils.py
django_mptt_comments/views.py
django_mptt_comments/migrations/0001_initial.py
django_mptt_comments/migrations/__init__.py
django_mptt_comments/static/css/django_mptt_comments.css
django_mptt_comments/static/js/django_mptt_comments.js
django_mptt_comments/templates/django_mptt_comments/base.html
django_mptt_comments/templates/django_mptt_comments/reply.html
django_mptt_comments/templatetags/__init__.py
django_mptt_comments/templatetags/mptt_comment_tags.py
django_mptt_comments-0.1.0.dist-info/DESCRIPTION.rst
django_mptt_comments-0.1.0.dist-info/METADATA
django_mptt_comments-0.1.0.dist-info/RECORD
django_mptt_comments-0.1.0.dist-info/WHEEL
django_mptt_comments-0.1.0.dist-info/metadata.json
django_mptt_comments-0.1.0.dist-info/top_level.txt
