Metadata-Version: 2.0
Name: django-mptt-comments
Version: 0.1.0
Summary: writting...
Home-page: https://github.com/zmrenwu/django-mptt-comments
Author: Xueguang Yang
Author-email: zmrenwu@163.com
License: MIT
Keywords: django-mptt-comments
Platform: UNKNOWN
Classifier: Development Status :: 3 - Alpha
Classifier: Framework :: Django :: 1.11
Classifier: Framework :: Django :: 2.0
Classifier: Intended Audience :: Developers
Classifier: License :: OSI Approved :: BSD License
Classifier: Natural Language :: English
Classifier: Programming Language :: Python :: 2
Classifier: Programming Language :: Python :: 2.7
Classifier: Programming Language :: Python :: 3
Classifier: Programming Language :: Python :: 3.4
Classifier: Programming Language :: Python :: 3.5
Classifier: Programming Language :: Python :: 3.6
Requires-Dist: django-model-utils (>=2.0)
Requires-Dist: django-model-utils (>=2.0)
Requires-Dist: bleach
Requires-Dist: markdown
Requires-Dist: django-simple-captcha
Requires-Dist: django-contrib-comments
Requires-Dist: django-mptt
Requires-Dist: django-crequest
